datedeux.py
datedeux-0.1.dist-info/LICENSE.txt
datedeux-0.1.dist-info/METADATA
datedeux-0.1.dist-info/WHEEL
datedeux-0.1.dist-info/top_level.txt
datedeux-0.1.dist-info/RECORD
