Metadata-Version: 2.1
Name: datedeux
Version: 0.1
Summary: Python date with glucose
Home-page: http://github.com/deepakkt/datedeux
Author: Deepak
Author-email: deepak@ktdpack.com
License: MIT
Platform: UNKNOWN
